Workbook

Sheet Resumen
A1: Club CIMA · Resumen del mes
A2: Se calcula solo con los datos de las hojas Socios y Planes.
A4: Plan | B4: Socios activos | C4: Ingreso esperado | D4: Ganancia esperada
A5: =Planes!A5 | B5: =COUNTIFS(Socios!$D$5:$D$204,Planes!A5,Socios!$G$5:$G$204,"Activo") | C5: =B5*Planes!B5 | D5: =B5*(Planes!B5-Planes!C5)
A6: =Planes!A6 | B6: =COUNTIFS(Socios!$D$5:$D$204,Planes!A6,Socios!$G$5:$G$204,"Activo") | C6: =B6*Planes!B6 | D6: =B6*(Planes!B6-Planes!C6)
A7: =Planes!A7 | B7: =COUNTIFS(Socios!$D$5:$D$204,Planes!A7,Socios!$G$5:$G$204,"Activo") | C7: =B7*Planes!B7 | D7: =B7*(Planes!B7-Planes!C7)
A8: Total | B8: =SUM(B5:B7) | C8: =SUM(C5:C7) | D8: =SUM(D5:D7)
A10: Cobrado este mes (activos que ya pagaron) | B10: =SUMIFS(Socios!$I$5:$I$204,Socios!$G$5:$G$204,"Activo",Socios!$H$5:$H$204,"Sí")
A11: Por cobrar este mes | B11: =C8-B10
A12: Socios activos que faltan pagar | B12: =COUNTIFS(Socios!$G$5:$G$204,"Activo",Socios!$H$5:$H$204,"No")+COUNTIFS(Socios!$G$5:$G$204,"Activo",Socios!$H$5:$H$204,"")
A13: Socios en pausa | B13: =COUNTIF(Socios!$G$5:$G$204,"Pausado")
A14: Socios que se dieron de baja | B14: =COUNTIF(Socios!$G$5:$G$204,"Baja")
A15: Ganancia esperada en un año (si se mantienen) | B15: =D8*12
A17: Nota: la fila de ejemplo de la hoja Socios cuenta en estos totales hasta que la borres.

Sheet Planes
A1: Club CIMA · Planes y costos
A2: Cambia solo las celdas AZULES con fondo AMARILLO. Los precios y costos son EJEMPLOS: reemplázalos por los tuyos.
A4: Plan | B4: Cuota mensual (Bs) | C4: Tu costo mensual por socio (Bs) | D4: Qué incluye / de dónde sale el costo
A5: Club CIMA | B5: 40 | C5: 18 | D5: Ejemplo. Costo: plantines del mes + nutrientes A+B+C + entrega.
A6: Club CIMA Plus | B6: 90 | C6: 45 | D6: Ejemplo. Costo: lo del Club + visita técnica cada 3 meses (prorrateada).
A7: Sistema en cuotas | B7: 130 | C7: 60 | D7: Ejemplo: torre de Bs 650 en 6 cuotas con Club incluido. Costo: torre (Bs 250 / 6) + Club.
A9: Estados de un socio
A10: Activo | D10: Recibe entregas y paga cada mes.
A11: Pausado | D11: Pidió una pausa: no recibe ni paga.
A12: Baja | D12: Dejó el Club.

Sheet Socios
A1: Club CIMA · Socios
A2: Una fila por socio. La fila 5 es un EJEMPLO: bórrala o reemplázala. "Cuota" se llena sola según el plan. Al empezar cada mes, cambia "Pagó este mes" a No.
A4: Nombre | B4: WhatsApp | C4: Zona | D4: Plan | E4: Fecha de inicio | F4: Día de entrega | G4: Estado | H4: Pagó este mes | I4: Cuota (Bs) | J4: Notas
A5: Ejemplo: María Quispe | B5: 70000000 | C5: El Alto - Villa Adela | D5: Club CIMA | E5: 2026-10-06 | F5: 5 | G5: Activo | H5: Sí | I5: =IF(D5="","",IFERROR(INDEX(Planes!$B$5:$B$7,MATCH(D5,Planes!$A$5:$A$7,0)),0)) | J5: Ejemplo: prefiere entrega en la tarde
I6: =IF(D6="","",IFERROR(INDEX(Planes!$B$5:$B$7,MATCH(D6,Planes!$A$5:$A$7,0)),0))
I7: =IF(D7="","",IFERROR(INDEX(Planes!$B$5:$B$7,MATCH(D7,Planes!$A$5:$A$7,0)),0))
I8: =IF(D8="","",IFERROR(INDEX(Planes!$B$5:$B$7,MATCH(D8,Planes!$A$5:$A$7,0)),0))
I9: =IF(D9="","",IFERROR(INDEX(Planes!$B$5:$B$7,MATCH(D9,Planes!$A$5:$A$7,0)),0))
I10: =IF(D10="","",IFERROR(INDEX(Planes!$B$5:$B$7,MATCH(D10,Planes!$A$5:$A$7,0)),0))
I11: =IF(D11="","",IFERROR(INDEX(Planes!$B$5:$B$7,MATCH(D11,Planes!$A$5:$A$7,0)),0))
I12: =IF(D12="","",IFERROR(INDEX(Planes!$B$5:$B$7,MATCH(D12,Planes!$A$5:$A$7,0)),0))
I13: =IF(D13="","",IFERROR(INDEX(Planes!$B$5:$B$7,MATCH(D13,Planes!$A$5:$A$7,0)),0))
I14: =IF(D14="","",IFERROR(INDEX(Planes!$B$5:$B$7,MATCH(D14,Planes!$A$5:$A$7,0)),0))
I15: =IF(D15="","",IFERROR(INDEX(Planes!$B$5:$B$7,MATCH(D15,Planes!$A$5:$A$7,0)),0))
I16: =IF(D16="","",IFERROR(INDEX(Planes!$B$5:$B$7,MATCH(D16,Planes!$A$5:$A$7,0)),0))
I17: =IF(D17="","",IFERROR(INDEX(Planes!$B$5:$B$7,MATCH(D17,Planes!$A$5:$A$7,0)),0))
... I204: =IF(D204="","",IFERROR(INDEX(Planes!$B$5:$B$7,MATCH(D204,Planes!$A$5:$A$7,0)),0))
