Workbook

Sheet Supuestos
A1: EcoAlaya · Supuestos del modelo de negocio (La Paz)
A2: Cómo usar: cambia solo las celdas con texto AZUL y fondo AMARILLO. Todo lo demás se calcula solo.
A3: Ejemplo | B3: 650 | C3: ← celda editable
A5: Sistemas
A6: Precio torre hidropónica | B6: 650 | D6: Dato de EcoAlaya (usuario).
A7: Costo de fabricar la torre | B7: 250 | D7: Dato de EcoAlaya (usuario).
A8: Precio sistema familiar NFT | B8: 850 | D8: Dato de EcoAlaya (usuario).
A9: Costo de fabricar el NFT | B9: 270 | D9: Dato de EcoAlaya (usuario).
A10: % de ventas que son torres | B10: 0.5 | D10: Supuesto: mitad torres y mitad NFT. El resto son NFT.
A11: Nutrientes
A12: Precio juego A+B+C de 200 L | B12: 40 | D12: Dato de EcoAlaya (usuario). También hay 500 L a Bs 60 y 1000 L a Bs 110.
A13: Litros de solución que rinde ese juego | B13: 200 | D13: Dato de EcoAlaya: 5 mL/L de A, B y C; concentrados de 5 L.
A14: Costo del juego de 200 L (materia prima + envase) | B14: 16 | D14: SUPUESTO: 40 % del precio. Reemplázalo por tu costo real.
A15: Litros de solución que usa un cliente al mes | B15: 50 | D15: Supuesto: tanque de 20 L cambiado cada 15 días (40 L) + 10 L de reposición.
A16: % de clientes que siguen comprando nutrientes | B16: 0.6 | D16: Supuesto: 6 de cada 10 clientes siguen cultivando y te compran a ti.
A17: Gastos mensuales
A18: Publicidad en redes (Facebook, TikTok, Instagram) | B18: 400 | D18: Supuesto de presupuesto inicial.
A19: Otros gastos fijos (transporte, entregas, datos) | B19: 200 | D19: Supuesto.
A20: Análisis
A21: Meses del análisis | B21: 12 | D21: Primer año.
A23: Resultados por unidad (calculados)
A24: Ganancia por torre | B24: =Supuestos!$B$6-Supuestos!$B$7
A25: Ganancia por NFT | B25: =Supuestos!$B$8-Supuestos!$B$9
A26: Precio promedio por sistema | B26: =Supuestos!$B$10*Supuestos!$B$6+(1-Supuestos!$B$10)*Supuestos!$B$8
A27: Ganancia promedio por sistema | B27: =Supuestos!$B$10*B24+(1-Supuestos!$B$10)*B25
A28: Margen promedio (%) | B28: =IF(B26=0,0,B27/B26)
A29: Meses que le dura un juego de 200 L a un cliente | B29: =IF(Supuestos!$B$15=0,0,Supuestos!$B$13/Supuestos!$B$15)
A30: Ingreso por nutrientes por cliente activo al mes | B30: =IF(B29=0,0,Supuestos!$B$12/B29)
A31: Ganancia por nutrientes por cliente activo al mes | B31: =IF(B29=0,0,(Supuestos!$B$12-Supuestos!$B$14)/B29)
A32: Gastos mensuales totales | B32: =Supuestos!$B$18+Supuestos!$B$19
A33: Sistemas al mes para no perder dinero (punto de equilibrio) | B33: =IF(B27<=0,0,ROUNDUP(B32/B27,0))

Sheet Escenarios
A1: EcoAlaya · Escenarios del primer año
A2: Cambia los sistemas vendidos por mes (azul, fondo amarillo). Supone ventas parejas cada mes.
A4: Concepto | B4: Pesimista | C4: Normal | D4: Optimista
A5: Sistemas vendidos por mes | B5: 2 | C5: 5 | D5: 10
A6: Sistemas vendidos en el año | B6: =B5*Supuestos!$B$21 | C6: =C5*Supuestos!$B$21 | D6: =D5*Supuestos!$B$21
A7: Ingreso por sistemas en el año | B7: =B6*Supuestos!$B$26 | C7: =C6*Supuestos!$B$26 | D7: =D6*Supuestos!$B$26
A8: Ganancia por sistemas en el año | B8: =B6*Supuestos!$B$27 | C8: =C6*Supuestos!$B$27 | D8: =D6*Supuestos!$B$27
A9: Clientes al final del año | B9: =B6 | C9: =C6 | D9: =D6
A10: Meses-cliente comprando nutrientes | B10: =B5*Supuestos!$B$21*(Supuestos!$B$21+1)/2*Supuestos!$B$16 | C10: =C5*Supuestos!$B$21*(Supuestos!$B$21+1)/2*Supuestos!$B$16 | D10: =D5*Supuestos!$B$21*(Supuestos!$B$21+1)/2*Supuestos!$B$16
A11: Ingreso por nutrientes en el año | B11: =B10*Supuestos!$B$30 | C11: =C10*Supuestos!$B$30 | D11: =D10*Supuestos!$B$30
A12: Ganancia por nutrientes en el año | B12: =B10*Supuestos!$B$31 | C12: =C10*Supuestos!$B$31 | D12: =D10*Supuestos!$B$31
A13: Gastos del año (publicidad + fijos) | B13: =Supuestos!$B$32*Supuestos!$B$21 | C13: =Supuestos!$B$32*Supuestos!$B$21 | D13: =Supuestos!$B$32*Supuestos!$B$21
A14: GANANCIA NETA DEL AÑO | B14: =B8+B12-B13 | C14: =C8+C12-C13 | D14: =D8+D12-D13
A15: Ganancia neta promedio por mes | B15: =IF(Supuestos!$B$21=0,0,B14/Supuestos!$B$21) | C15: =IF(Supuestos!$B$21=0,0,C14/Supuestos!$B$21) | D15: =IF(Supuestos!$B$21=0,0,D14/Supuestos!$B$21)
A16: Ingreso por nutrientes en el último mes | B16: =B5*Supuestos!$B$21*Supuestos!$B$16*Supuestos!$B$30 | C16: =C5*Supuestos!$B$21*Supuestos!$B$16*Supuestos!$B$30 | D16: =D5*Supuestos!$B$21*Supuestos!$B$16*Supuestos!$B$30
A18: Punto de equilibrio: sistemas al mes para cubrir los gastos | B18: =Supuestos!$B$33
A20: Notas
A21: • Los clientes empiezan a comprar nutrientes el mes en que compran su sistema.
A22: • Los sistemas vendidos por mes son supuestos; cámbialos cuando tengas ventas reales.
A23: • No incluye semillas, ampliaciones, talleres ni ventas a colegios, que serían ingresos extra.

Sheet Proyección
A1: EcoAlaya · Proyección mes a mes
A2: Escenario (1 = pesimista, 2 = normal, 3 = optimista): | F2: 2 | G2: =INDEX(Escenarios!$B$4:$D$4,1,$F$2)
A3: Sistemas por mes en este escenario: | F3: =INDEX(Escenarios!$B$5:$D$5,1,$F$2)
A5: Mes | B5: Sistemas vendidos | C5: Ingreso sistemas | D5: Ganancia sistemas | E5: Clientes acumulados | F5: Clientes activos (nutrientes) | G5: Ganancia nutrientes | H5: Gastos | I5: Ganancia neta acumulada
A6: 1 | B6: =$F$3 | C6: =B6*Supuestos!$B$26 | D6: =B6*Supuestos!$B$27 | E6: =B6 | F6: =E6*Supuestos!$B$16 | G6: =F6*Supuestos!$B$31 | H6: =Supuestos!$B$32 | I6: =D6+G6-H6
A7: 2 | B7: =$F$3 | C7: =B7*Supuestos!$B$26 | D7: =B7*Supuestos!$B$27 | E7: =E6+B7 | F7: =E7*Supuestos!$B$16 | G7: =F7*Supuestos!$B$31 | H7: =Supuestos!$B$32 | I7: =I6+D7+G7-H7
A8: 3 | B8: =$F$3 | C8: =B8*Supuestos!$B$26 | D8: =B8*Supuestos!$B$27 | E8: =E7+B8 | F8: =E8*Supuestos!$B$16 | G8: =F8*Supuestos!$B$31 | H8: =Supuestos!$B$32 | I8: =I7+D8+G8-H8
A9: 4 | B9: =$F$3 | C9: =B9*Supuestos!$B$26 | D9: =B9*Supuestos!$B$27 | E9: =E8+B9 | F9: =E9*Supuestos!$B$16 | G9: =F9*Supuestos!$B$31 | H9: =Supuestos!$B$32 | I9: =I8+D9+G9-H9
A10: 5 | B10: =$F$3 | C10: =B10*Supuestos!$B$26 | D10: =B10*Supuestos!$B$27 | E10: =E9+B10 | F10: =E10*Supuestos!$B$16 | G10: =F10*Supuestos!$B$31 | H10: =Supuestos!$B$32 | I10: =I9+D10+G10-H10
A11: 6 | B11: =$F$3 | C11: =B11*Supuestos!$B$26 | D11: =B11*Supuestos!$B$27 | E11: =E10+B11 | F11: =E11*Supuestos!$B$16 | G11: =F11*Supuestos!$B$31 | H11: =Supuestos!$B$32 | I11: =I10+D11+G11-H11
A12: 7 | B12: =$F$3 | C12: =B12*Supuestos!$B$26 | D12: =B12*Supuestos!$B$27 | E12: =E11+B12 | F12: =E12*Supuestos!$B$16 | G12: =F12*Supuestos!$B$31 | H12: =Supuestos!$B$32 | I12: =I11+D12+G12-H12
A13: 8 | B13: =$F$3 | C13: =B13*Supuestos!$B$26 | D13: =B13*Supuestos!$B$27 | E13: =E12+B13 | F13: =E13*Supuestos!$B$16 | G13: =F13*Supuestos!$B$31 | H13: =Supuestos!$B$32 | I13: =I12+D13+G13-H13
A14: 9 | B14: =$F$3 | C14: =B14*Supuestos!$B$26 | D14: =B14*Supuestos!$B$27 | E14: =E13+B14 | F14: =E14*Supuestos!$B$16 | G14: =F14*Supuestos!$B$31 | H14: =Supuestos!$B$32 | I14: =I13+D14+G14-H14
A15: 10 | B15: =$F$3 | C15: =B15*Supuestos!$B$26 | D15: =B15*Supuestos!$B$27 | E15: =E14+B15 | F15: =E15*Supuestos!$B$16 | G15: =F15*Supuestos!$B$31 | H15: =Supuestos!$B$32 | I15: =I14+D15+G15-H15
A16: 11 | B16: =$F$3 | C16: =B16*Supuestos!$B$26 | D16: =B16*Supuestos!$B$27 | E16: =E15+B16 | F16: =E16*Supuestos!$B$16 | G16: =F16*Supuestos!$B$31 | H16: =Supuestos!$B$32 | I16: =I15+D16+G16-H16
A17: 12 | B17: =$F$3 | C17: =B17*Supuestos!$B$26 | D17: =B17*Supuestos!$B$27 | E17: =E16+B17 | F17: =E17*Supuestos!$B$16 | G17: =F17*Supuestos!$B$31 | H17: =Supuestos!$B$32 | I17: =I16+D17+G17-H17
A18: Total | B18: =SUM(B6:B17) | C18: =SUM(C6:C17) | D18: =SUM(D6:D17) | G18: =SUM(G6:G17) | H18: =SUM(H6:H17) | I18: =I17
